SCellBOW/SCellBOW.py
SCellBOW/__init__.py
SCellBOW-1.2.2.dist-info/LICENSE
SCellBOW-1.2.2.dist-info/METADATA
SCellBOW-1.2.2.dist-info/WHEEL
SCellBOW-1.2.2.dist-info/top_level.txt
SCellBOW-1.2.2.dist-info/RECORD
