Metadata-Version: 2.1
Name: SCellBOW
Version: 1.2.2
Summary: SCellBOW is an unsupervised transfer learning algorithm for clustering scRNA-seq data and performing phenotype algebra analysis on the clusters
Home-page: https://github.com/cellsemantics/SCellBOW
Author: NAMRATA BHATTACHARYA, SAM KOSHY THOMAS, DEBARKA SENGUPTA
Author-email: namrata.bhattacharya@hdr.qut.edu.au, samkoshy.thomas@student.adelaide.edu.au, debarka@iiitd.ac.in
License: Apache License 2.0
Platform: UNKNOWN
Requires-Dist: numpy
Requires-Dist: pandas
Requires-Dist: gensim
Requires-Dist: scanpy
Requires-Dist: nltk
Requires-Dist: scikit-learn
Requires-Dist: scikit-survival
Requires-Dist: imbalanced-learn
Requires-Dist: xgbse
Requires-Dist: tqdm
Requires-Dist: matplotlib
